MANIFEST.in
README.rst
distribute_setup.py
setup.py
docs/demo.py
python_sisow.egg-info/PKG-INFO
python_sisow.egg-info/SOURCES.txt
python_sisow.egg-info/dependency_links.txt
python_sisow.egg-info/requires.txt
python_sisow.egg-info/top_level.txt
sisow/__init__.py
tests/__init__.py
tests/tests.py
tests/transaction.py