Metadata-Version: 1.1
Name: python-sisow
Version: 0.1.2
Summary: Python programming interface to Sisow, Dutch iDeal Payment Service Provider
Home-page: https://github.com/nederhoed/python-sisow
Author: Robert-Reinder Nederhoed
Author-email: r.r.nederhoed@gmail.com
License: GPLv3
Keywords: ideal sisow finance
Platform: UNKNOWN
Classifier: Development Status :: 2 - Pre-Alpha
Classifier: Programming Language :: Python
Classifier: License :: OSI Approved :: GNU General Public License v3 (GPLv3)
